BugsInPy/__init__.py
BugsInPy/bgp.py
BugsInPy/bgp_config.py
BugsInPy/class_extractor.py
BugsInPy/exceptions.py
BugsInPy/extract_localistion_set.py
BugsInPy/lmeasures.py
BugsInPy/run_custom_patch.py
BugsInPy/sample_bip.py
BugsInPy/test_runner.py
BugsInPy/utils.py
BugsInPy/feature_extractor/__init__.py
BugsInPy/feature_extractor/dynamic_features.py
BugsInPy/feature_extractor/file_instrumenter.py
BugsInPy/feature_extractor/static_features.py
diff_utils/__init__.py
diff_utils/diff_utils.py
diff_utils/diff_utils_test.py
static_library/__init__.py
static_library/static_utils.py
pyr_benchmark_wrangling-0.0.11.dist-info/METADATA
pyr_benchmark_wrangling-0.0.11.dist-info/WHEEL
pyr_benchmark_wrangling-0.0.11.dist-info/entry_points.txt
pyr_benchmark_wrangling-0.0.11.dist-info/top_level.txt
pyr_benchmark_wrangling-0.0.11.dist-info/RECORD
