Metadata-Version: 2.1
Name: pyr_benchmark_wrangling
Version: 0.0.11
Summary: A package to facilitate data-wrangling for APR tools
Home-page: https://github.com/PyRepair/pyr_benchmark_wrangling
Author: PyRepair Team
Author-email: nikhil.parasaram.19@ucl.ac.uk
License: Apache License 2.0
Classifier: Programming Language :: Python :: 3
Classifier: Programming Language :: Python :: 3.10
Classifier: Programming Language :: Python :: 3.11
Classifier: Programming Language :: Python :: 3.12
Classifier: License :: OSI Approved :: Apache Software License
Classifier: Operating System :: OS Independent
Requires-Python: >=3.10
Requires-Dist: absl-py <2.0.0,>=1.0.0
Requires-Dist: GitPython <4.0.0,>=3.0.0
